GeoBaseMain.py
LICENSE
MANIFEST.in
README
README.rst
RELEASE_NOTES.rst
VERSION
setup.py
GeoBases/GeoBaseModule.py
GeoBases/GeoGridModule.py
GeoBases/GeoUtils.py
GeoBases/LevenshteinUtils.py
GeoBases/SourcesManagerModule.py
GeoBases/VisualMixinModule.py
GeoBases/__init__.py
GeoBases/DashboardAssets/dashboard.js
GeoBases/DashboardAssets/nv.d3.css
GeoBases/DashboardAssets/nv.d3.min.js
GeoBases/DashboardAssets/template.html
GeoBases/DataSources/CheckDataUpdates.sh
GeoBases/DataSources/Sources.yaml
GeoBases/DataSources/Aircraft/optd_aircraft.csv
GeoBases/DataSources/Airlines/optd_airlines.csv
GeoBases/DataSources/Airports/GeoNames/README.txt
GeoBases/DataSources/Airports/GeoNames/airports_geonames_only_clean.csv
GeoBases/DataSources/Cabins/cabins.csv
GeoBases/DataSources/Cities/cities15000.zip
GeoBases/DataSources/Continents/continentCodes.txt
GeoBases/DataSources/Countries/README.txt
GeoBases/DataSources/Countries/capitals.csv
GeoBases/DataSources/Countries/countryInfo.txt
GeoBases/DataSources/Currencies/wiki_source_ISO_4217.csv
GeoBases/DataSources/FeatureClasses/feature_classes.csv
GeoBases/DataSources/FeatureCodes/featureCodes_en.txt
GeoBases/DataSources/Languages/iso-languagecodes.txt
GeoBases/DataSources/Locales/locales.csv
GeoBases/DataSources/LocationTypes/location_types.csv
GeoBases/DataSources/Por/GeoNames/FR.zip
GeoBases/DataSources/Por/GeoNames/MC.zip
GeoBases/DataSources/Por/GeoNames/README.txt
GeoBases/DataSources/Por/Optd/optd_por_no_longer_valid.csv
GeoBases/DataSources/Por/Optd/optd_por_public.csv
GeoBases/DataSources/PostalCodes/GeoNames/FR.zip
GeoBases/DataSources/PostalCodes/GeoNames/MC.zip
GeoBases/DataSources/Regions/optd_region_details.csv
GeoBases/DataSources/TimeZones/timeZones.txt
GeoBases/DataSources/TrainStations/README.txt
GeoBases/DataSources/TrainStations/DataGouvFr/RFF_gares.ids.gm.man.red.csv
GeoBases/DataSources/TrainStations/NLS/NLS_CODES_RefDataSNCF.csv
GeoBases/DataSources/TrainStations/UIC/sncfExtract_v1.0.csv
GeoBasesDev.egg-info/PKG-INFO
GeoBasesDev.egg-info/SOURCES.txt
GeoBasesDev.egg-info/dependency_links.txt
GeoBasesDev.egg-info/entry_points.txt
GeoBasesDev.egg-info/requires.txt
GeoBasesDev.egg-info/top_level.txt
