Metadata-Version: 1.1
Name: GeoBasesDev
Version: 6.0.0a28
Summary: Data services and visualization - development version
Home-page: http://opentraveldata.github.com/geobases
Author: Alex Prengère
Author-email: geobases.dev@gmail.com
License: Creative Commons
